tacklebox_webhooks.py
apis/error.py
apis/event_api.py
apis/event_type_api.py
apis/http_client.py
apis/http_request.py
apis/message_api.py
apis/service_api.py
apis/subscription_api.py
apis/user_api.py
build/lib/tacklebox_webhooks.py
build/lib/apis/error.py
build/lib/apis/event_api.py
build/lib/apis/event_type_api.py
build/lib/apis/http_client.py
build/lib/apis/http_request.py
build/lib/apis/message_api.py
build/lib/apis/service_api.py
build/lib/apis/subscription_api.py
build/lib/apis/user_api.py
build/lib/build/lib/tacklebox_webhooks.py
build/lib/build/lib/apis/error.py
build/lib/build/lib/apis/event_api.py
build/lib/build/lib/apis/event_type_api.py
build/lib/build/lib/apis/http_client.py
build/lib/build/lib/apis/http_request.py
build/lib/build/lib/apis/message_api.py
build/lib/build/lib/apis/service_api.py
build/lib/build/lib/apis/subscription_api.py
build/lib/build/lib/apis/user_api.py
build/lib/build/lib/build/lib/tacklebox_webhooks.py
build/lib/build/lib/build/lib/apis/error.py
build/lib/build/lib/build/lib/apis/event_api.py
build/lib/build/lib/build/lib/apis/event_type_api.py
build/lib/build/lib/build/lib/apis/http_client.py
build/lib/build/lib/build/lib/apis/http_request.py
build/lib/build/lib/build/lib/apis/message_api.py
build/lib/build/lib/build/lib/apis/service_api.py
build/lib/build/lib/build/lib/apis/subscription_api.py
build/lib/build/lib/build/lib/apis/user_api.py
build/lib/build/lib/build/lib/build/lib/tacklebox_webhooks.py
build/lib/build/lib/build/lib/build/lib/apis/error.py
build/lib/build/lib/build/lib/build/lib/apis/event_api.py
build/lib/build/lib/build/lib/build/lib/apis/event_type_api.py
build/lib/build/lib/build/lib/build/lib/apis/http_client.py
build/lib/build/lib/build/lib/build/lib/apis/http_request.py
build/lib/build/lib/build/lib/build/lib/apis/message_api.py
build/lib/build/lib/build/lib/build/lib/apis/service_api.py
build/lib/build/lib/build/lib/build/lib/apis/subscription_api.py
build/lib/build/lib/build/lib/build/lib/apis/user_api.py
tacklebox_webhooks-0.1.3.dist-info/LICENSE.txt
tacklebox_webhooks-0.1.3.dist-info/METADATA
tacklebox_webhooks-0.1.3.dist-info/WHEEL
tacklebox_webhooks-0.1.3.dist-info/top_level.txt
tacklebox_webhooks-0.1.3.dist-info/RECORD
