Metadata-Version: 2.1
Name: tacklebox-webhooks
Version: 0.1.3
Summary: An open-source serverless framework that offers webhooks as a service.
Home-page: https://github.com/tacklebox-webhooks/python
Author: Juan Palma, Kayl Thomas, Kevin Counihan, Armando Mota
Author-email: juanpedropalma@hotmail.com
License: MIT
Platform: UNKNOWN
Requires-Dist: requests
